Missing_data_101883059/Missing_values_removal_using_SImpleImputer.py
Missing_data_101883059/__init__.py
Missing_data_101883059_Priyanshu_Tuli-0.0.1.dist-info/LICENSE
Missing_data_101883059_Priyanshu_Tuli-0.0.1.dist-info/METADATA
Missing_data_101883059_Priyanshu_Tuli-0.0.1.dist-info/WHEEL
Missing_data_101883059_Priyanshu_Tuli-0.0.1.dist-info/top_level.txt
Missing_data_101883059_Priyanshu_Tuli-0.0.1.dist-info/RECORD
