Metadata-Version: 2.1
Name: Missing-data-101883059-Priyanshu-Tuli
Version: 0.0.1
Summary: A package for removing missing data from a dataset using Simple Imputer class
Home-page: https://github.com/Priyanshu0/Missing_data_removal_using_SimpleImputer
Author: Priyanshu Tuli
Author-email: priyanshu1tuli@gmail.com
License: UNKNOWN
Platform: UNKNOWN
Classifier: Programming Language :: Python :: 3
Classifier: License :: OSI Approved :: MIT License
Classifier: Operating System :: OS Independent
Requires-Python: >=3.6
